{
  "title": "マカオから中国・珠海へ！宿泊費・食費を抑えるスマート移動ガイド",
  "content": "<h2>1. マカオから拱北口岸（珠海）への行き方</h2>\n      <p>マカオ半島北端の關閘（Barrier Gate）から徒歩で中国側の拱北口岸（Gongbei Port）へ渡るルートがもっともポピュラーです。マカオ市内から關閘へは下記の手段が一般的。</p>\n      <ul>\n        <li><strong>路線バス：</strong>主要路線が關閘方面へ運行。運賃はおおむね数パタカ〜十数パタカ程度。</li>\n        <li><strong>タクシー：</strong>市街地から約10〜20分。荷物が多い場合は便利。</li>\n        <li><strong>徒歩：</strong>中心部から徒歩圏内の宿も多く、荷物が少なければ歩いて行けます。</li>\n      </ul>\n      <p>關閘到着後、マカオの出境審査を受け、徒歩で拱北口岸側の入境審査場へ向かいます。移動はスムーズで案内表示も充実しています。</p>\n\n```\n\n```",
  "category": "overseas",
  "image": "/contents/photo/kyoto2.jpg",
  "slug": "10001",
  "excerpt": "test"
}